spanetlib/__init__.py
spanetlib/const.py
spanetlib/spanet.py
spanetlib-1.0.5.dist-info/LICENSE
spanetlib-1.0.5.dist-info/METADATA
spanetlib-1.0.5.dist-info/WHEEL
spanetlib-1.0.5.dist-info/top_level.txt
spanetlib-1.0.5.dist-info/RECORD
