Metadata-Version: 2.1
Name: spanetlib
Version: 1.0.5
Summary: A package that handles communication with SpaNET Spas
Home-page: https://github.com/enheron/spanet
Author: spanet
Author-email: en@herontechnology.co.nz
Classifier: Programming Language :: Python :: 3
Classifier: License :: OSI Approved :: MIT License
Classifier: Operating System :: OS Independent
License-File: LICENSE
